LICENSE
MANIFEST.in
README.md
requirements.txt
setup.py
luaproject/__init__.py
luaproject/cli.py
luaproject/manager.py
luaproject.egg-info/PKG-INFO
luaproject.egg-info/SOURCES.txt
luaproject.egg-info/dependency_links.txt
luaproject.egg-info/entry_points.txt
luaproject.egg-info/not-zip-safe
luaproject.egg-info/requires.txt
luaproject.egg-info/top_level.txt
luaproject/example/.gitignore
luaproject/example/LICENSE
luaproject/example/MANIFEST.in
luaproject/example/README.md
luaproject/example/manage_package_clean_name.py
luaproject/example/requirements.txt
luaproject/example/setup.py
luaproject/example/example/__init__.py
luaproject/example/example/src/.rockspec
luaproject/example/example/src/lua/handler.lua
luaproject/example/example/src/lua/schema.lua