Metadata-Version: 2.1
Name: luaproject
Version: 0.3.3
Summary: Use python package to manage LUA plugin, so that the plugin can be published to private pypi server and used internally. A temporary solution for PYTHONER using kong.
Home-page: https://github.com/zencore-cn/zencore-issues
Author: zencore
Author-email: dobetter@zencore.cn
License: MIT
Keywords: luaproject
Platform: UNKNOWN
Classifier: Development Status :: 5 - Production/Stable
Classifier: Intended Audience :: Developers
Classifier: Topic :: Software Development :: Libraries :: Python Modules
Classifier: License :: OSI Approved :: MIT License
Classifier: Programming Language :: Python :: 3
Classifier: Programming Language :: Python :: 3 :: Only
